{
    "props": {
        "data": {
            "id": "__row_index__",
            "projection": {
                "x": "projection_v3_x",
                "y": "projection_v3_y"
            }
        },
        "embeddingViewLabels": [
            {
                "x": -0.8964325893010459,
                "y": -0.02823811231022202,
                "text": "Language Models & Pretraining",
                "level": 0,
                "priority": 10
            },
            {
                "x": -2.9620713137042243,
                "y": -0.8820360227807692,
                "text": "Computer Vision",
                "level": 0,
                "priority": 10
            },
            {
                "x": 1.2485929902871873,
                "y": -0.1971549323019341,
                "text": "Multimodal Learning",
                "level": 0,
                "priority": 10
            },
            {
                "x": -0.29213762644873154,
                "y": 0.7894460933952258,
                "text": "Reinforcement Learning",
                "level": 0,
                "priority": 10
            },
            {
                "x": -3.0128314515203813,
                "y": 0.8137317023549571,
                "text": "Robotics & Embodied AI",
                "level": 0,
                "priority": 10
            },
            {
                "x": 1.1221705172843608,
                "y": 1.3561304283895783,
                "text": "Safety, Alignment & Ethics",
                "level": 0,
                "priority": 10
            },
            {
                "x": -1.3960461300125842,
                "y": 1.421536475885026,
                "text": "Theory, Optimization & Efficient ML",
                "level": 0,
                "priority": 10
            },
            {
                "x": 3.026536222070437,
                "y": -0.6738386984532125,
                "text": "Domain Applications",
                "level": 0,
                "priority": 10
            },
            {
                "x": -3.0844806921653913,
                "y": -0.0047307302431442745,
                "text": "Generative Models & Synthesis",
                "level": 0,
                "priority": 10
            },
            {
                "x": 2.436191366890902,
                "y": 0.8345373370521276,
                "text": "Speech & Audio Processing",
                "level": 0,
                "priority": 10
            },
            {
                "x": 1.6196231157525809,
                "y": -1.2387824579451032,
                "text": "Graph Learning & Networks",
                "level": 0,
                "priority": 10
            },
            {
                "x": -0.21964662987494965,
                "y": -1.5435375620584662,
                "text": "Data, Benchmarks & Evaluation",
                "level": 0,
                "priority": 10
            },
            {
                "x": 3.33852606474736,
                "y": 0.19889686858743222,
                "text": "Human-AI Interaction",
                "level": 0,
                "priority": 10
            },
            {
                "x": -1.0155157816149765,
                "y": -0.8835427147095698,
                "text": "Planning & Search",
                "level": 0,
                "priority": 10
            }
        ]
    },
    "isStatic": true,
    "database": {
        "type": "wasm",
        "load": true
    },
    "name_column": "title",
    "label_column": "title",
    "color_by": "Prominence",
    "column_mappings": {
        "title": "title",
        "abstract": "abstract",
        "Prominence": "Prominence",
        "author_count": "author_count",
        "author_tier": "author_tier",
        "url": "url",
        "ss_citation_count": "ss_citation_count",
        "ss_influential_citations": "ss_influential_citations",
        "ss_tldr": "ss_tldr",
        "CitationTier": "CitationTier",
        "recency": "recency",
        "paper_source": "paper_source"
    }
}